consibio_cloud_client/__init__.py
consibio_cloud_client/client.py
consibio_cloud_client/project.py
consibio_cloud_client/models/DataFrame.py
consibio_cloud_client/models/SingleValue.py
consibio_cloud_client/models/__init__.py
consibio_cloud_client/utils/log.py
consibio_cloud_client-1.0.0.dist-info/LICENSE.txt
consibio_cloud_client-1.0.0.dist-info/METADATA
consibio_cloud_client-1.0.0.dist-info/WHEEL
consibio_cloud_client-1.0.0.dist-info/top_level.txt
consibio_cloud_client-1.0.0.dist-info/RECORD
